ragbot/__init__.py
ragbot/cli.py
ragbot/document_loader.py
ragbot/ragbot_api.py
ragbot/ret.py
ragbot/static/chat.html
ragbot/static/chat_window.html
ragbot/static/index.html
ragbot-0.1.0.dist-info/METADATA
ragbot-0.1.0.dist-info/WHEEL
ragbot-0.1.0.dist-info/entry_points.txt
ragbot-0.1.0.dist-info/top_level.txt
ragbot-0.1.0.dist-info/RECORD
