Metadata-Version: 2.4
Name: ragbot
Version: 0.1.0
Summary: RAG chatbot for companies using local docs and websites
Author: Preethi Chappidi
Author-email: 22b1074@iitb.ac.in
Classifier: Programming Language :: Python :: 3
Classifier: Operating System :: OS Independent
Requires-Dist: langchain
Requires-Dist: langchain-community
Requires-Dist: langchain-huggingface
Requires-Dist: faiss-cpu
Requires-Dist: llama-cpp-python
Requires-Dist: fastapi
Requires-Dist: uvicorn
Requires-Dist: beautifulsoup4
Requires-Dist: requests
Requires-Dist: sentence-transformers
Requires-Dist: python-multipart
Requires-Dist: tqdm
Requires-Dist: nltk
Requires-Dist: unstructured
Requires-Dist: python-magic
Requires-Dist: tiktoken
Dynamic: author
Dynamic: author-email
Dynamic: classifier
Dynamic: requires-dist
Dynamic: summary
